LICENSE.txt
README.md
setup.cfg
setup.py
DjangoIntellitextFormField/IntellitextFormField.py
DjangoIntellitextFormField/__init__.py
DjangoIntellitextFormField/_version.py
DjangoIntellitextFormField.egg-info/PKG-INFO
DjangoIntellitextFormField.egg-info/SOURCES.txt
DjangoIntellitextFormField.egg-info/dependency_links.txt
DjangoIntellitextFormField.egg-info/top_level.txt